denovonear/__init__.py
denovonear/__main__.py
denovonear/cluster_test.py
denovonear/ensembl_cache.py
denovonear/ensembl_requester.py
denovonear/frameshift_rate.py
denovonear/load_de_novos.py
denovonear/load_gene.py
denovonear/load_mutation_rates.py
denovonear/log_transform_rates.py
denovonear/rate_limiter.py
denovonear/rate_limiter_retries.py
denovonear/simulate.py
denovonear/site_specific_rates.cp311-win_amd64.pyd
denovonear/site_specific_rates.cpp
denovonear/site_specific_rates.pyx
denovonear/structures.py
denovonear/weights.cp311-win_amd64.pyd
denovonear/weights.cpp
denovonear/weights.pxd
denovonear/weights.pyx
denovonear/data/__init__.py
denovonear/data/rates.txt
denovonear-0.12.0.dist-info/licenses/LICENSE.txt
denovonear-0.12.0.dist-info/METADATA
denovonear-0.12.0.dist-info/WHEEL
denovonear-0.12.0.dist-info/entry_points.txt
denovonear-0.12.0.dist-info/top_level.txt
denovonear-0.12.0.dist-info/RECORD
