Metadata-Version: 2.4
Name: denovonear
Version: 0.12.0
Summary: Package to examine de novo clustering
Author-email: Jeremy McRae <jeremy.mcrae@gmail.com>
Project-URL: homepage, https://github.com/jeremymcrae/denovonear
Classifier: Development Status :: 5 - Production/Stable
Classifier: Topic :: Scientific/Engineering :: Bio-Informatics
Classifier: License :: OSI Approved :: MIT License
Requires-Python: >=3.9
License-File: LICENSE.txt
Requires-Dist: aiohttp>=3.9.0b0
Requires-Dist: scipy>=0.9.0
Requires-Dist: gencodegenes>=1.0.10
Provides-Extra: pysam
Requires-Dist: pysam; extra == "pysam"
Dynamic: license-file
